aipkgs_sendgrid/__init__.py
aipkgs_sendgrid/helpers.py
aipkgs_sendgrid-1.0.6.dist-info/LICENSE.md
aipkgs_sendgrid-1.0.6.dist-info/METADATA
aipkgs_sendgrid-1.0.6.dist-info/WHEEL
aipkgs_sendgrid-1.0.6.dist-info/RECORD
